threatbus_vast/__init__.py
threatbus_vast/message_mapping.py
threatbus_vast/plugin.py
threatbus_vast/setup.py
threatbus_vast/test_message_mapping.py
threatbus_vast-2020.9.30.dist-info/COPYING
threatbus_vast-2020.9.30.dist-info/METADATA
threatbus_vast-2020.9.30.dist-info/WHEEL
threatbus_vast-2020.9.30.dist-info/entry_points.txt
threatbus_vast-2020.9.30.dist-info/top_level.txt
threatbus_vast-2020.9.30.dist-info/RECORD
