Metadata-Version: 2.1
Name: threatbus-vast
Version: 2020.9.30
Summary: A plugin to enable threatbus communication with VAST.
Home-page: https://github.com/tenzir/threatbus
Author: Tenzir
Author-email: engineering@tenzir.com
License: BSD 3-clause
Keywords: threatbus,vast,threat intelligence,zeromq
Platform: UNKNOWN
Classifier: Development Status :: 3 - Alpha
Classifier: Environment :: Plugins
Classifier: License :: OSI Approved :: BSD License
Classifier: Operating System :: MacOS :: MacOS X
Classifier: Operating System :: POSIX :: Linux
Classifier: Programming Language :: Python :: 3
Classifier: Topic :: Scientific/Engineering :: Information Analysis
Classifier: Topic :: Scientific/Engineering :: Interface Engine/Protocol Translator
Classifier: Topic :: Security
Classifier: Topic :: Software Development :: Object Brokering
Classifier: Topic :: System :: Distributed Computing
Requires-Python: >=3.7
Requires-Dist: threatbus (>=2020.09.30)
Requires-Dist: pyzmq (>=19)
Requires-Dist: python-dateutil (>=2.8.1)
